LICENSE
MANIFEST.in
README.md
setup.py
django_socialshareprivacy.egg-info/PKG-INFO
django_socialshareprivacy.egg-info/SOURCES.txt
django_socialshareprivacy.egg-info/dependency_links.txt
django_socialshareprivacy.egg-info/requires.txt
django_socialshareprivacy.egg-info/top_level.txt
socialshareprivacy/__init__.py
socialshareprivacy/models.py
socialshareprivacy/static/socialshareprivacy/2-klick-logo_min.jpg
socialshareprivacy/static/socialshareprivacy/dimensions.gif
socialshareprivacy/static/socialshareprivacy/index.html
socialshareprivacy/static/socialshareprivacy/jquery.socialshareprivacy.js
socialshareprivacy/static/socialshareprivacy/jquery.socialshareprivacy.min.js
socialshareprivacy/static/socialshareprivacy/jquery.socialshareprivacy.zip
socialshareprivacy/static/socialshareprivacy/socialshareprivacy.css
socialshareprivacy/static/socialshareprivacy/images/2-klick-logo.jpg
socialshareprivacy/static/socialshareprivacy/images/dummy_facebook.png
socialshareprivacy/static/socialshareprivacy/images/dummy_facebook_dark.png
socialshareprivacy/static/socialshareprivacy/images/dummy_facebook_en.png
socialshareprivacy/static/socialshareprivacy/images/dummy_facebook_like.png
socialshareprivacy/static/socialshareprivacy/images/dummy_facebook_share_de.png
socialshareprivacy/static/socialshareprivacy/images/dummy_facebook_share_de_dark.png
socialshareprivacy/static/socialshareprivacy/images/dummy_facebook_share_en.png
socialshareprivacy/static/socialshareprivacy/images/dummy_facebook_share_en_dark.png
socialshareprivacy/static/socialshareprivacy/images/dummy_gplus.png
socialshareprivacy/static/socialshareprivacy/images/dummy_gplus_alt.png
socialshareprivacy/static/socialshareprivacy/images/dummy_gplus_dark.png
socialshareprivacy/static/socialshareprivacy/images/dummy_twitter.png
socialshareprivacy/static/socialshareprivacy/images/dummy_twitter_dark.png
socialshareprivacy/static/socialshareprivacy/images/facebook_share_de.png
socialshareprivacy/static/socialshareprivacy/images/facebook_share_de_dark.png
socialshareprivacy/static/socialshareprivacy/images/facebook_share_en.png
socialshareprivacy/static/socialshareprivacy/images/facebook_share_en_dark.png
