Metadata-Version: 1.1
Name: django-socialshareprivacy
Version: 1.5.1
Summary: A Django application for the heise.de socialshareprivacy jQuery plugin.
Home-page: http://github.com/adsworth/django-socialshareprivacy/
Author: Adi Sieker
Author-email: adi@sieker.io
License: LICENSE
Platform: OS Independent
Classifier: Environment :: Web Environment
Classifier: Framework :: Django
Classifier: Intended Audience :: Developers
Classifier: License :: OSI Approved :: BSD License
Classifier: Operating System :: OS Independent
Classifier: Programming Language :: Python
Classifier: Topic :: Software Development :: Libraries :: Application Frameworks
